[
  {
    "id": 1,
    "name": "Sarah Johnson",
    "title": "CEO",
    "address": "1234 Main Avenue, Anytown, USA"
  },
  {
    "id": 2,
    "name": "Christopher Brown",
    "title": "CTO",
    "address": "5678 Elm Street, Othertown, USA"
  },
  {
    "id": 3,
    "name": "Olivia Wilson",
    "title": "CFO",
    "address": "91011 Oak Lane, Anycity, USA"
  },
  {
    "id": 4,
    "name": "Ethan Smith",
    "title": "COO",
    "address": "121314 Pine Drive, Anothercity, USA"
  },
  {
    "id": 5,
    "name": "Ava Martinez",
    "title": "CMO",
    "address": "151617 Cedar Court, Somewhereville, USA"
  },
  {
    "id": 6,
    "name": "Noah Anderson",
    "title": "Marketing Director",
    "address": "181920 Maple Road, Downtown, USA"
  },
  {
    "id": 7,
    "name": "Sophia Thompson",
    "title": "Product Manager",
    "address": "212223 Birch Lane, Suburbia, USA"
  },
  {
    "id": 8,
    "name": "Liam Davis",
    "title": "Software Engineer",
    "address": "242526 Walnut Avenue, Uptown, USA"
  },
  {
    "id": 9,
    "name": "Emma Rodriguez",
    "title": "UI/UX Designer",
    "address": "272829 Ash Road, Countryside, USA"
  },
  {
    "id": 10,
    "name": "James Garcia",
    "title": "HR Manager",
    "address": "303132 Pine Lane, Seaside, USA"
  },
  {
    "id": 11,
    "name": "Mia Hernandez",
    "title": "Sales Representative",
    "address": "333435 Oak Drive, Hillside, USA"
  },
  {
    "id": 12,
    "name": "Lucas Lopez",
    "title": "Accountant",
    "address": "363738 Cedar Court, Lakeside, USA"
  },
  {
    "id": 13,
    "name": "Isabella Perez",
    "title": "Customer Support Specialist",
    "address": "394041 Elm Lane, Riverside, USA"
  },
  {
    "id": 14,
    "name": "William Miller",
    "title": "Data Analyst",
    "address": "424344 Maple Road, Mountainside, USA"
  },
  {
    "id": 15,
    "name": "Charlotte Taylor",
    "title": "Operations Manager",
    "address": "454647 Birch Avenue, Hilltop, USA"
  },
  {
    "id": 16,
    "name": "Benjamin Martinez",
    "title": "Project Manager",
    "address": "484950 Walnut Road, Oceanview, USA"
  },
  {
    "id": 17,
    "name": "Amelia Lewis",
    "title": "Quality Assurance Engineer",
    "address": "515253 Ash Lane, Countryside, USA"
  },
  {
    "id": 18,
    "name": "Jacob Walker",
    "title": "Technical Writer",
    "address": "545556 Pine Drive, Seaside, USA"
  },
  {
    "id": 19,
    "name": "Harper Hall",
    "title": "Business Analyst",
    "address": "575859 Oak Lane, Hillside, USA"
  },
  {
    "id": 20,
    "name": "Emma Clark",
    "title": "Scrum Master",
    "address": "606162 Cedar Court, Lakeside, USA"
  },
  {
    "id": 21,
    "name": "Daniel Adams",
    "title": "DevOps Engineer",
    "address": "636465 Elm Road, Riverside, USA"
  },
  {
    "id": 22,
    "name": "Sophie Young",
    "title": "Software Developer",
    "address": "666768 Maple Lane, Mountainside, USA"
  },
  {
    "id": 23,
    "name": "Michael Green",
    "title": "UI/UX Designer",
    "address": "697071 Birch Drive, Hilltop, USA"
  },
  {
    "id": 24,
    "name": "Ava Allen",
    "title": "Product Manager",
    "address": "727374 Walnut Lane, Oceanview, USA"
  },
  {
    "id": 25,
    "name": "Ethan Brown",
    "title": "HR Manager",
    "address": "757677 Ash Avenue, Countryside, USA"
  }
]
